selsearch/__init__.py
selsearch/app.py
selsearch/environ.py
selsearch/gui.py
selsearch/main.py
selsearch/search.py
selsearch/selection.py
selsearch/where.py
selsearch-0.1.5.dist-info/LICENSE.md
selsearch-0.1.5.dist-info/METADATA
selsearch-0.1.5.dist-info/WHEEL
selsearch-0.1.5.dist-info/top_level.txt
selsearch-0.1.5.dist-info/RECORD
