Metadata-Version: 2.1
Name: selsearch
Version: 0.1.5
Summary: Internet search based on selected text
Home-page: https://github.com/jeertmans/selsearch
Author: Jérome Eertmans
Author-email: jeertmans@icloud.com
License: MIT
Platform: UNKNOWN
Classifier: Programming Language :: Python :: 3
Classifier: License :: OSI Approved :: MIT License
Classifier: Operating System :: OS Independent
Requires-Python: >=3.6
License-File: LICENSE.md
Requires-Dist: click (==8.0.3)
Requires-Dist: pyperclip (==1.8.2)
Requires-Dist: pynput (==1.7.6)
